photonvision/__init__.py
photonvision/_init_photonvision.py
photonvision/_photonvision.cpython-310-x86_64-linux-gnu.so
photonvision/pkgcfg.py
photonvision/py.typed
photonvision/version.py
photonvision/__pycache__/__init__.cpython-310.pyc
photonvision/__pycache__/_init_photonvision.cpython-310.pyc
photonvision/__pycache__/version.cpython-310.pyc
photonvision/_photonvision/__init__.pyi
photonvision/_photonvision/target_sort_mode/__init__.pyi
photonvision/include/LICENSE
photonvision/include/PhotonVersion.h
photonvision/include/photonlib/Packet.h
photonvision/include/photonlib/PhotonCamera.h
photonvision/include/photonlib/PhotonPipelineResult.h
photonvision/include/photonlib/PhotonPoseEstimator.h
photonvision/include/photonlib/PhotonTargetSortMode.h
photonvision/include/photonlib/PhotonTrackedTarget.h
photonvision/include/photonlib/PhotonUtils.h
photonvision/include/photonlib/RobotPoseEstimator.h
photonvision/include/photonlib/SimPhotonCamera.h
photonvision/include/photonlib/SimVisionSystem.h
photonvision/include/photonlib/SimVisionTarget.h
photonvision/rpy-include/rpygen/photonlib__PhotonCamera.hpp
photonvision/src/headers.patch
photonvision/src/module.cpp
photonvision/src/sources.patch
robotpy_photonvision-2023.4.2.dist-info/LICENSE
robotpy_photonvision-2023.4.2.dist-info/METADATA
robotpy_photonvision-2023.4.2.dist-info/WHEEL
robotpy_photonvision-2023.4.2.dist-info/entry_points.txt
robotpy_photonvision-2023.4.2.dist-info/top_level.txt
robotpy_photonvision-2023.4.2.dist-info/RECORD
