Metadata-Version: 2.1
Name: robotpy-photonvision
Version: 2023.4.2
Summary: RobotPy wrappers for photonvision
Home-page: https://github.com/robotpy/robotpy-photonvision
Author: RobotPy Development Team
Author-email: robotpy@googlegroups.com
License: MIT
Requires-Python: >=3.6
License-File: LICENSE
Requires-Dist: pyntcore (<2024.0.0,>=2023.4.1)
Requires-Dist: robotpy-apriltag (<2024.0.0,>=2023.4.1)
Requires-Dist: robotpy-wpimath (<2024.0.0,>=2023.4.1)
Requires-Dist: wpilib (<2024.0.0,>=2023.4.1)
